plavchan.cpython-313-x86_64-linux-gnu.so
plavchan_gpu/__init__.py
plavchan_gpu/plavchan.cu
plavchan_gpu.libs/libcudart-381c0faa.so.12.9.37
plavchan_gpu-1.1.2.dist-info/METADATA
plavchan_gpu-1.1.2.dist-info/WHEEL
plavchan_gpu-1.1.2.dist-info/top_level.txt
plavchan_gpu-1.1.2.dist-info/RECORD
plavchan_gpu-1.1.2.dist-info/licenses/LICENSE
