Metadata-Version: 2.4
Name: plavchan_gpu
Version: 1.1.2
Summary: GPU-accelerated Plavchan periodogram calculation
Author-email: Matteo Paz <matteopi314@gmail.com>
License: MIT
Project-URL: Homepage, https://github.com/matteopaz/plavchan-gpu
Project-URL: Repository, https://github.com/matteopaz/plavchan-gpu
Classifier: Programming Language :: Python :: 3
Classifier: License :: OSI Approved :: MIT License
Classifier: Operating System :: POSIX :: Linux
Classifier: Intended Audience :: Science/Research
Classifier: Topic :: Scientific/Engineering :: Astronomy
Requires-Python: >=3.6
License-File: LICENSE
Dynamic: license-file
